setup.py
git_version.egg-info/PKG-INFO
git_version.egg-info/SOURCES.txt
git_version.egg-info/dependency_links.txt
git_version.egg-info/entry_points.txt
git_version.egg-info/top_level.txt
gitversionbuilder/DummyVersion.py
gitversionbuilder/Version.py
gitversionbuilder/__init__.py
gitversionbuilder/__main__.py
gitversionbuilder/main.py
gitversionbuilder/utils.py
gitversionbuilder/versioninfo.py
gitversionbuilder/versioninfooutputter.py
gitversionbuilder/versioninforeader.py
test/test_utils.py