Metadata-Version: 1.1
Name: git-version
Version: 1.5
Summary: Make git version information (e.g. git tag name, git commit id, ...) available to your C++ or python source files. A simple use case scenario is to output this version information when the application is called with "--version".
Home-page: https://github.com/smessmer/gitversion
Author: Sebastian Messmer
Author-email: heinzisoft@web.de
License: GPLv3
Platform: UNKNOWN
Classifier: Development Status :: 5 - Production/Stable
Classifier: Environment :: Console
Classifier: Intended Audience :: Developers
Classifier: License :: OSI Approved :: GNU General Public License v3 (GPLv3)
Classifier: Programming Language :: Python
Classifier: Programming Language :: C++
Classifier: Topic :: Software Development :: Build Tools
Classifier: Topic :: Software Development :: Code Generators
Classifier: Topic :: Software Development :: Version Control
